{
  "last_updated": "2025-02-04T23:49:42.379Z",
  "current": {
    "city": "Samarate",
    "date": "2/5/2025, 12:49:42 AM",
    "temperature": "3.53?C",
    "feels_like": "3.53?C",
    "pressure": "1031 hPa",
    "humidity": "91%",
    "min_temperature": "2.16?C",
    "max_temperature": "4.9?C",
    "wind_speed": "1.3 m/s",
    "wind_direction": "324?",
    "visibility": "10 km",
    "cloudiness": "0%",
    "weather_description": "clear sky",
    "weather_id": 800
  },
  "forecast": [
    {
      "date": "2025-02-05",
      "average_temperature": "6.37",
      "feels_like": "6.13",
      "pressure": "1031.88",
      "humidity": "60.63",
      "wind_speed": "0.94",
      "wind_direction": "267.63",
      "cloudiness": "0.25",
      "weather": "clear sky",
      "weather_id": 800
    },
    {
      "date": "2025-02-06",
      "average_temperature": "6.78",
      "feels_like": "5.91",
      "pressure": "1031.63",
      "humidity": "49.25",
      "wind_speed": "1.41",
      "wind_direction": "53.75",
      "cloudiness": "9.63",
      "weather": "clear sky",
      "weather_id": 800
    },
    {
      "date": "2025-02-07",
      "average_temperature": "5.09",
      "feels_like": "4.47",
      "pressure": "1029.00",
      "humidity": "71.50",
      "wind_speed": "1.31",
      "wind_direction": "68.50",
      "cloudiness": "96.13",
      "weather": "overcast clouds",
      "weather_id": 804
    },
    {
      "date": "2025-02-08",
      "average_temperature": "4.12",
      "feels_like": "2.42",
      "pressure": "1028.63",
      "humidity": "90.50",
      "wind_speed": "2.16",
      "wind_direction": "261.75",
      "cloudiness": "100.00",
      "weather": "light rain",
      "weather_id": 500
    },
    {
      "date": "2025-02-09",
      "average_temperature": "7.03",
      "feels_like": "6.49",
      "pressure": "1029.88",
      "humidity": "72.25",
      "wind_speed": "1.32",
      "wind_direction": "257.00",
      "cloudiness": "97.38",
      "weather": "overcast clouds",
      "weather_id": 804
    }
  ]
}