{
  "last_updated": "2025-03-04T05:49:38.668Z",
  "current": {
    "city": "Samarate",
    "date": "3/4/2025, 6:49:38 AM",
    "temperature": "2.79?C",
    "feels_like": "0.54?C",
    "pressure": "1026 hPa",
    "humidity": "86%",
    "min_temperature": "1.66?C",
    "max_temperature": "4.37?C",
    "wind_speed": "2.24 m/s",
    "wind_direction": "21?",
    "visibility": "10 km",
    "cloudiness": "0%",
    "weather_description": "clear sky",
    "weather_id": 800
  },
  "forecast": [
    {
      "date": "2025-03-05",
      "average_temperature": "10.52",
      "feels_like": "9.29",
      "pressure": "1027.50",
      "humidity": "48.88",
      "wind_speed": "0.99",
      "wind_direction": "168.88",
      "cloudiness": "15.38",
      "weather": "few clouds",
      "weather_id": 801
    },
    {
      "date": "2025-03-06",
      "average_temperature": "10.67",
      "feels_like": "9.75",
      "pressure": "1027.25",
      "humidity": "54.50",
      "wind_speed": "1.13",
      "wind_direction": "128.75",
      "cloudiness": "63.13",
      "weather": "overcast clouds",
      "weather_id": 804
    },
    {
      "date": "2025-03-07",
      "average_temperature": "10.53",
      "feels_like": "9.61",
      "pressure": "1022.13",
      "humidity": "54.88",
      "wind_speed": "0.99",
      "wind_direction": "176.50",
      "cloudiness": "46.13",
      "weather": "clear sky",
      "weather_id": 800
    },
    {
      "date": "2025-03-08",
      "average_temperature": "10.81",
      "feels_like": "9.87",
      "pressure": "1017.50",
      "humidity": "53.75",
      "wind_speed": "0.80",
      "wind_direction": "286.00",
      "cloudiness": "0.50",
      "weather": "clear sky",
      "weather_id": 800
    },
    {
      "date": "2025-03-09",
      "average_temperature": "8.82",
      "feels_like": "8.82",
      "pressure": "1015.50",
      "humidity": "59.50",
      "wind_speed": "1.19",
      "wind_direction": "352.00",
      "cloudiness": "21.00",
      "weather": "scattered clouds",
      "weather_id": 802
    }
  ]
}