{
  "last_updated": "2025-03-02T14:49:38.503Z",
  "current": {
    "city": "Samarate",
    "date": "3/2/2025, 3:49:38 PM",
    "temperature": "13.3?C",
    "feels_like": "12.04?C",
    "pressure": "1028 hPa",
    "humidity": "52%",
    "min_temperature": "12.28?C",
    "max_temperature": "14.34?C",
    "wind_speed": "3.09 m/s",
    "wind_direction": "220?",
    "visibility": "10 km",
    "cloudiness": "20%",
    "weather_description": "light rain",
    "weather_id": 500
  },
  "forecast": [
    {
      "date": "2025-03-03",
      "average_temperature": "8.76",
      "feels_like": "8.00",
      "pressure": "1028.00",
      "humidity": "57.88",
      "wind_speed": "0.91",
      "wind_direction": "294.00",
      "cloudiness": "18.13",
      "weather": "clear sky",
      "weather_id": 800
    },
    {
      "date": "2025-03-04",
      "average_temperature": "9.66",
      "feels_like": "8.90",
      "pressure": "1026.25",
      "humidity": "48.75",
      "wind_speed": "0.99",
      "wind_direction": "249.13",
      "cloudiness": "30.00",
      "weather": "clear sky",
      "weather_id": 800
    },
    {
      "date": "2025-03-05",
      "average_temperature": "10.22",
      "feels_like": "9.47",
      "pressure": "1027.50",
      "humidity": "51.13",
      "wind_speed": "0.93",
      "wind_direction": "133.75",
      "cloudiness": "24.25",
      "weather": "clear sky",
      "weather_id": 800
    },
    {
      "date": "2025-03-06",
      "average_temperature": "9.99",
      "feels_like": "9.42",
      "pressure": "1028.38",
      "humidity": "58.13",
      "wind_speed": "0.94",
      "wind_direction": "75.75",
      "cloudiness": "69.38",
      "weather": "overcast clouds",
      "weather_id": 804
    },
    {
      "date": "2025-03-07",
      "average_temperature": "8.94",
      "feels_like": "8.62",
      "pressure": "1024.80",
      "humidity": "59.40",
      "wind_speed": "1.04",
      "wind_direction": "248.20",
      "cloudiness": "30.00",
      "weather": "scattered clouds",
      "weather_id": 802
    }
  ]
}