{
  "last_updated": "2025-01-07T14:49:38.810Z",
  "current": {
    "city": "Samarate",
    "date": "1/7/2025, 3:49:38 PM",
    "temperature": "7.74?C",
    "feels_like": "6.51?C",
    "pressure": "1008 hPa",
    "humidity": "84%",
    "min_temperature": "6.18?C",
    "max_temperature": "8.79?C",
    "wind_speed": "2.06 m/s",
    "wind_direction": "230?",
    "visibility": "10 km",
    "cloudiness": "40%",
    "weather_description": "scattered clouds",
    "weather_id": 802
  },
  "forecast": [
    {
      "date": "2025-01-08",
      "average_temperature": "4.80",
      "feels_like": "4.02",
      "pressure": "1013.50",
      "humidity": "65.13",
      "wind_speed": "1.31",
      "wind_direction": "330.50",
      "cloudiness": "67.25",
      "weather": "overcast clouds",
      "weather_id": 804
    },
    {
      "date": "2025-01-09",
      "average_temperature": "5.58",
      "feels_like": "4.94",
      "pressure": "1010.88",
      "humidity": "82.50",
      "wind_speed": "1.35",
      "wind_direction": "249.25",
      "cloudiness": "71.38",
      "weather": "scattered clouds",
      "weather_id": 802
    },
    {
      "date": "2025-01-10",
      "average_temperature": "5.46",
      "feels_like": "4.55",
      "pressure": "1015.75",
      "humidity": "70.25",
      "wind_speed": "1.45",
      "wind_direction": "116.88",
      "cloudiness": "27.25",
      "weather": "few clouds",
      "weather_id": 801
    },
    {
      "date": "2025-01-11",
      "average_temperature": "6.12",
      "feels_like": "5.39",
      "pressure": "1015.13",
      "humidity": "74.00",
      "wind_speed": "1.47",
      "wind_direction": "239.88",
      "cloudiness": "39.13",
      "weather": "broken clouds",
      "weather_id": 803
    },
    {
      "date": "2025-01-12",
      "average_temperature": "4.25",
      "feels_like": "2.83",
      "pressure": "1026.00",
      "humidity": "63.60",
      "wind_speed": "1.76",
      "wind_direction": "182.00",
      "cloudiness": "63.20",
      "weather": "broken clouds",
      "weather_id": 803
    }
  ]
}