{
  "last_updated": "2025-03-07T02:49:38.477Z",
  "current": {
    "city": "Samarate",
    "date": "3/7/2025, 3:49:38 AM",
    "temperature": "8.12?C",
    "feels_like": "7.45?C",
    "pressure": "1024 hPa",
    "humidity": "60%",
    "min_temperature": "6.06?C",
    "max_temperature": "8.79?C",
    "wind_speed": "1.55 m/s",
    "wind_direction": "5?",
    "visibility": "10 km",
    "cloudiness": "13%",
    "weather_description": "few clouds",
    "weather_id": 801
  },
  "forecast": [
    {
      "date": "2025-03-08",
      "average_temperature": "11.26",
      "feels_like": "10.31",
      "pressure": "1017.50",
      "humidity": "53.25",
      "wind_speed": "1.03",
      "wind_direction": "168.25",
      "cloudiness": "54.25",
      "weather": "broken clouds",
      "weather_id": 803
    },
    {
      "date": "2025-03-09",
      "average_temperature": "10.61",
      "feels_like": "9.75",
      "pressure": "1012.88",
      "humidity": "56.88",
      "wind_speed": "1.11",
      "wind_direction": "108.88",
      "cloudiness": "88.63",
      "weather": "overcast clouds",
      "weather_id": 804
    },
    {
      "date": "2025-03-10",
      "average_temperature": "8.34",
      "feels_like": "7.66",
      "pressure": "1006.50",
      "humidity": "83.13",
      "wind_speed": "1.54",
      "wind_direction": "213.00",
      "cloudiness": "100.00",
      "weather": "overcast clouds",
      "weather_id": 804
    },
    {
      "date": "2025-03-11",
      "average_temperature": "8.54",
      "feels_like": "8.54",
      "pressure": "1003.88",
      "humidity": "85.75",
      "wind_speed": "0.86",
      "wind_direction": "43.38",
      "cloudiness": "100.00",
      "weather": "light rain",
      "weather_id": 500
    },
    {
      "date": "2025-03-12",
      "average_temperature": "8.08",
      "feels_like": "8.08",
      "pressure": "1002.00",
      "humidity": "86.00",
      "wind_speed": "0.86",
      "wind_direction": "350.00",
      "cloudiness": "100.00",
      "weather": "light rain",
      "weather_id": 500
    }
  ]
}