{
  "last_updated": "2025-05-31T19:49:38.312Z",
  "current": {
    "city": "Samarate",
    "date": "5/31/2025, 9:49:38 PM",
    "temperature": "23.46?C",
    "feels_like": "23.69?C",
    "pressure": "1019 hPa",
    "humidity": "70%",
    "min_temperature": "22.44?C",
    "max_temperature": "24.34?C",
    "wind_speed": "1.03 m/s",
    "wind_direction": "120?",
    "visibility": "10 km",
    "cloudiness": "0%",
    "weather_description": "clear sky",
    "weather_id": 800
  },
  "forecast": [
    {
      "date": "2025-06-01",
      "average_temperature": "23.70",
      "feels_like": "23.93",
      "pressure": "1017.88",
      "humidity": "68.50",
      "wind_speed": "1.54",
      "wind_direction": "176.88",
      "cloudiness": "68.25",
      "weather": "light rain",
      "weather_id": 500
    },
    {
      "date": "2025-06-02",
      "average_temperature": "19.82",
      "feels_like": "20.03",
      "pressure": "1017.75",
      "humidity": "83.25",
      "wind_speed": "0.79",
      "wind_direction": "210.00",
      "cloudiness": "98.13",
      "weather": "light rain",
      "weather_id": 500
    },
    {
      "date": "2025-06-03",
      "average_temperature": "18.87",
      "feels_like": "19.15",
      "pressure": "1016.38",
      "humidity": "89.50",
      "wind_speed": "1.09",
      "wind_direction": "105.75",
      "cloudiness": "87.25",
      "weather": "light rain",
      "weather_id": 500
    },
    {
      "date": "2025-06-04",
      "average_temperature": "17.61",
      "feels_like": "17.83",
      "pressure": "1015.50",
      "humidity": "92.13",
      "wind_speed": "1.24",
      "wind_direction": "192.38",
      "cloudiness": "95.88",
      "weather": "light rain",
      "weather_id": 500
    },
    {
      "date": "2025-06-05",
      "average_temperature": "17.17",
      "feels_like": "17.19",
      "pressure": "1015.14",
      "humidity": "86.29",
      "wind_speed": "1.53",
      "wind_direction": "211.29",
      "cloudiness": "91.14",
      "weather": "light rain",
      "weather_id": 500
    }
  ]
}